MANIFEST.in
birdseed.py
setup.cfg
setup.py
birdseed.egg-info/PKG-INFO
birdseed.egg-info/SOURCES.txt
birdseed.egg-info/dependency_links.txt
birdseed.egg-info/requires.txt
birdseed.egg-info/top_level.txt