Metadata-Version: 1.1
Name: birdseed
Version: 0.2.0
Summary: Twitter random number seeder/generator
Home-page: https://github.com/ryanmcdermott/birdseed
Author: Ryan McDermott
Author-email: ryan.mcdermott@ryansworks.com
License: MIT
Keywords: random sysadmin development
Platform: UNKNOWN
Classifier: Development Status :: 3 - Alpha
Classifier: Intended Audience :: Developers
Classifier: Topic :: Utilities
Classifier: License :: OSI Approved :: MIT License
Classifier: Programming Language :: Python :: 2
Classifier: Programming Language :: Python :: 2.6
Classifier: Programming Language :: Python :: 2.7
Classifier: Programming Language :: Python :: 3
Classifier: Programming Language :: Python :: 3.2
Classifier: Programming Language :: Python :: 3.3
Classifier: Programming Language :: Python :: 3.4
